Workbook

Sheet Cover
B1: Blu Containers
B4: Discounted Cash Flow Valuation Model
B6: ENGAGEMENT DETAILS
B7: Valuation Date | E7: 46226
B8: Reporting Currency | E8: US$ in millions
B9: Model Type | E9: 5-Year DCF — exit-multiple terminal value
B10: Prepared By | E10: Chungu Kapambwe
B11: Status | E11: Final
B13: VALUATION SUMMARY
B14: Implied Value per Share (US$) | E14: =Model!O420 -> 12.252247
B15: Current Share Price (US$) | E15: =Assumptions!N8 -> 11.5
B16: Implied Premium / (Discount) | E16: =Model!O426 -> 0.065412801
B18: CONTENTS
B19: Summary | E19: Scenario output — Base, Best, Worst
B20: Assumptions | E20: Key operating & valuation inputs
B21: Scenarios | E21: Scenario switch and driver sets
B22: Model | E22: Integrated 3-statement model & DCF valuation
B23: Income Tax | E23: Corporate income tax computation
B24: Variable vs. Fixed Costs | E24: Cost behaviour split
B25: Semi-Variable Costs | E25: Semi-variable cost detail
B27: This model is prepared for illustrative and analytical purposes only and does not constitute investment advice. Figures are estimates based on stated assumptions and are subject to change. Confidential — for internal use only.

Sheet Summary
B1: =Cover!B1 -> Blu Containers
B2: Summary Outputs
C5: SUMMARY VALUES - BASE CASE | T5: ="SUMMMARY VALUES - "&UPPER(CHOOSE(Scenarios!$E$6,Scenarios!D14,Scenarios!D15,Scenarios!D16)) -> SUMMMARY VALUES - BASE CASE
K6: Projected | AA6: Projected
D7: ($ Millions) | F7: Trend | H7: =X7 -> 2024 | I7: =Y7 -> 2025 | J7: =Z7 -> 2026 | K7: =AA7 -> 2027 | L7: =AB7 -> 2028 | M7: =AC7 -> 2029 | N7: =AD7 -> 2030 | O7: =AE7 -> 2031 | X7: =Model!H7 -> 2024 | Y7: =Model!I7 -> 2025 | Z7: =Model!J7 -> 2026 | AA7: =Model!K7 -> 2027 | AB7: =Model!L7 -> 2028 | AC7: =Model!M7 -> 2029 | AD7: =Model!N7 -> 2030 | AE7: =Model!O7 -> 2031
D10: Income Statement Items | U10: Income Statement Items
E12: Net Revenue | H12: 213.5 | I12: 236.6 | J12: 204.8 | K12: 239.80282 | L12: 261.79321 | M12: 281.109 | N12: 277.03083 | O12: 268.03514 | V12: Net Revenue | W12: (MM) | X12: =Model!H85 -> 213.5 | Y12: =Model!I85 -> 236.6 | Z12: =Model!J85 -> 204.8 | AA12: =Model!K85 -> 239.80282 | AB12: =Model!L85 -> 261.79321 | AC12: =Model!M85 -> 281.109 | AD12: =Model!N85 -> 277.03083 | AE12: =Model!O85 -> 268.03514
E13: Growth | I13: =(I12-H12)/H12 -> 0.10819672 | J13: =(J12-I12)/I12 -> -0.13440406 | K13: =(K12-J12)/J12 -> 0.17091222 | L13: =(L12-K12)/K12 -> 0.091701961 | M13: =(M12-L12)/L12 -> 0.073782636 | N13: =(N12-M12)/M12 -> -0.014507445 | O13: =(O12-N12)/N12 -> -0.032471792 | V13: Growth | W13: (%) | Y13: =(Y12-X12)/X12 -> 0.10819672 | Z13: =(Z12-Y12)/Y12 -> -0.13440406 | AA13: =(AA12-Z12)/Z12 -> 0.17091222 | AB13: =(AB12-AA12)/AA12 -> 0.091701961 | AC13: =(AC12-AB12)/AB12 -> 0.073782636 | AD13: =(AD12-AC12)/AC12 -> -0.014507445 | AE13: =(AE12-AD12)/AD12 -> -0.032471792
E16: EBITDA | H16: 50.2 | I16: 68.4 | J16: 33.1 | K16: 61.215968 | L16: 75.322596 | M16: 85.761917 | N16: 71.909633 | O16: 53.575455 | V16: EBITDA | W16: (MM) | X16: =Model!H92 -> 50.2 | Y16: =Model!I92 -> 68.4 | Z16: =Model!J92 -> 33.1 | AA16: =Model!K92 -> 61.215968 | AB16: =Model!L92 -> 75.322596 | AC16: =Model!M92 -> 85.761917 | AD16: =Model!N92 -> 71.909633 | AE16: =Model!O92 -> 53.575455
E17: Margin | H17: =H16/H12 -> 0.23512881 | I17: =I16/I12 -> 0.28909552 | J17: =J16/J12 -> 0.16162109 | K17: =K16/K12 -> 0.25527626 | L17: =L16/L12 -> 0.28771791 | M17: =M16/M12 -> 0.3050842 | N17: =N16/N12 -> 0.25957267 | O17: =O16/O12 -> 0.1998822 | V17: Margin | W17: (%) | X17: =X16/X12 -> 0.23512881 | Y17: =Y16/Y12 -> 0.28909552 | Z17: =Z16/Z12 -> 0.16162109 | AA17: =AA16/AA12 -> 0.25527626 | AB17: =AB16/AB12 -> 0.28771791 | AC17: =AC16/AC12 -> 0.3050842 | AD17: =AD16/AD12 -> 0.25957267 | AE17: =AE16/AE12 -> 0.1998822
E18: Growth | I18: =(I16-H16)/H16 -> 0.3625498 | J18: =(J16-I16)/I16 -> -0.51608187 | K18: =(K16-J16)/J16 -> 0.84942501 | L18: =(L16-K16)/K16 -> 0.23044034 | M18: =(M16-L16)/L16 -> 0.13859481 | N18: =(N16-M16)/M16 -> -0.16152022 | O18: =(O16-N16)/N16 -> -0.25496136 | V18: Growth | W18: (%) | Y18: =(Y16-X16)/X16 -> 0.3625498 | Z18: =(Z16-Y16)/Y16 -> -0.51608187 | AA18: =(AA16-Z16)/Z16 -> 0.84942501 | AB18: =(AB16-AA16)/AA16 -> 0.23044034 | AC18: =(AC16-AB16)/AB16 -> 0.13859481 | AD18: =(AD16-AC16)/AC16 -> -0.16152022 | AE18: =(AE16-AD16)/AD16 -> -0.25496136
E21: Net Income | H21: 14.1 | I21: 23.7 | J21: 2.2 | K21: 21.478796 | L21: 31.029908 | M21: 38.527846 | N21: 30.288468 | O21: 18.965989 | V21: Net Income | W21: (MM) | X21: =Model!H104 -> 14.1 | Y21: =Model!I104 -> 23.7 | Z21: =Model!J104 -> 2.2 | AA21: =Model!K104 -> 21.478796 | AB21: =Model!L104 -> 31.029908 | AC21: =Model!M104 -> 38.527846 | AD21: =Model!N104 -> 30.288468 | AE21: =Model!O104 -> 18.965989
E22: Margin | H22: =H21/H12 -> 0.066042155 | I22: =I21/I12 -> 0.10016906 | J22: =J21/J12 -> 0.010742187 | K22: =K21/K12 -> 0.089568569 | L22: =L21/L12 -> 0.11852831 | M22: =M21/M12 -> 0.13705661 | N22: =N21/N12 -> 0.10933248 | O22: =O21/O12 -> 0.070759336 | V22: Margin | W22: (%) | X22: =X21/X12 -> 0.066042155 | Y22: =Y21/Y12 -> 0.10016906 | Z22: =Z21/Z12 -> 0.010742187 | AA22: =AA21/AA12 -> 0.089568569 | AB22: =AB21/AB12 -> 0.11852831 | AC22: =AC21/AC12 -> 0.13705661 | AD22: =AD21/AD12 -> 0.10933248 | AE22: =AE21/AE12 -> 0.070759336
E23: Growth | I23: =(I21-H21)/H21 -> 0.68085106 | J23: =(J21-I21)/I21 -> -0.907173 | K23: =(K21-J21)/J21 -> 8.763089 | L23: =(L21-K21)/K21 -> 0.44467632 | M23: =(M21-L21)/L21 -> 0.24163586 | N23: =(N21-M21)/M21 -> -0.21385514 | O23: =(O21-N21)/N21 -> -0.37382146 | V23: Growth | W23: (%) | Y23: =(Y21-X21)/X21 -> 0.68085106 | Z23: =(Z21-Y21)/Y21 -> -0.907173 | AA23: =(AA21-Z21)/Z21 -> 8.763089 | AB23: =(AB21-AA21)/AA21 -> 0.44467632 | AC23: =(AC21-AB21)/AB21 -> 0.24163586 | AD23: =(AD21-AC21)/AC21 -> -0.21385514 | AE23: =(AE21-AD21)/AD21 -> -0.37382146
C26: SUMMARY VALUES - BEST CASE
K27: Projected
D28: ($ Millions) | F28: Trend | H28: =H7 -> 2024 | I28: =I7 -> 2025 | J28: =J7 -> 2026 | K28: =K7 -> 2027 | L28: =L7 -> 2028 | M28: =M7 -> 2029 | N28: =N7 -> 2030 | O28: =O7 -> 2031
D31: Income Statement Items
E33: Net Revenue | H33: 213.5 | I33: 236.6 | J33: 204.8 | K33: 250.94298 | L33: 273.9837 | M33: 297.21532 | N33: 296.10532 | O33: 281.50084
E34: Growth | I34: =(I33-H33)/H33 -> 0.10819672 | J34: =(J33-I33)/I33 -> -0.13440406 | K34: =(K33-J33)/J33 -> 0.22530754 | L34: =(L33-K33)/K33 -> 0.091816523 | M34: =(M33-L33)/L33 -> 0.084791975 | N34: =(N33-M33)/M33 -> -0.0037346636 | O34: =(O33-N33)/N33 -> -0.049321881
E37: EBITDA | H37: 50.2 | I37: 68.4 | J37: 33.1 | K37: 72.356129 | L37: 87.878709 | M37: 102.0651 | N37: 90.95238 | O37: 70.580713
E38: Margin | H38: =H37/H33 -> 0.23512881 | I38: =I37/I33 -> 0.28909552 | J38: =J37/J33 -> 0.16162109 | K38: =K37/K33 -> 0.28833693 | L38: =L37/L33 -> 0.3207443 | M38: =M37/M33 -> 0.34340456 | N38: =N37/N33 -> 0.30716227 | O38: =O37/O33 -> 0.25073002
E39: Growth | I39: =(I37-H37)/H37 -> 0.3625498 | J39: =(J37-I37)/I37 -> -0.51608187 | K39: =(K37-J37)/J37 -> 1.1859858 | L39: =(L37-K37)/K37 -> 0.21453027 | M39: =(M37-L37)/L37 -> 0.16143144 | N39: =(N37-M37)/M37 -> -0.10887871 | O39: =(O37-N37)/N37 -> -0.22398168
E42: Net Income | H42: 14.1 | I42: 23.7 | J42: 2.2 | K42: 28.719901 | L42: 39.360168 | M42: 49.300648 | N42: 42.7919 | O42: 30.207765
E43: Margin | H43: =H42/H33 -> 0.066042155 | I43: =I42/I33 -> 0.10016906 | J43: =J42/J33 -> 0.010742187 | K43: =K42/K33 -> 0.11444791 | L43: =L42/L33 -> 0.1436588 | M43: =M42/M33 -> 0.1658752 | N43: =N42/N33 -> 0.14451581 | O43: =O42/O33 -> 0.10730968
E44: Growth | I44: =(I42-H42)/H42 -> 0.68085106 | J44: =(J42-I42)/I42 -> -0.907173 | K44: =(K42-J42)/J42 -> 12.0545 | L44: =(L42-K42)/K42 -> 0.37048415 | M44: =(M42-L42)/L42 -> 0.25255177 | N44: =(N42-M42)/M42 -> -0.13202157 | O44: =(O42-N42)/N42 -> -0.2940775
C47: SUMMARY VALUES - WORST CASE
K48: Projected
D49: ($ Millions) | F49: Trend | H49: =H28 -> 2024 | I49: =I28 -> 2025 | J49: =J28 -> 2026 | K49: =K28 -> 2027 | L49: =L28 -> 2028 | M49: =M28 -> 2029 | N49: =N28 -> 2030 | O49: =O28 -> 2031
D52: Income Statement Items
E53: Net Revenue | H53: 213.5 | I53: 236.6 | J53: 204.8 | K53: 226.37745 | L53: 246.99646 | M53: 262.60854 | N53: 256.14161 | O53: 244.66998
E54: Growth | I54: =(I53-H53)/H53 -> 0.10819672 | J54: =(J53-I53)/I53 -> -0.13440406 | K54: =(K53-J53)/J53 -> 0.10535863 | L54: =(L53-K53)/K53 -> 0.09108245 | M54: =(M53-L53)/L53 -> 0.063207717 | N54: =(N53-M53)/M53 -> -0.024625743 | O54: =(O53-N53)/N53 -> -0.044786282
E57: EBITDA | H57: 50.2 | I57: 68.4 | J57: 33.1 | K57: 48.797134 | L57: 60.684745 | M57: 68.207666 | N57: 53.258047 | O57: 34.164574
E58: Margin | H58: =H57/H53 -> 0.23512881 | I58: =I57/I53 -> 0.28909552 | J58: =J57/J53 -> 0.16162109 | K58: =K57/K53 -> 0.21555652 | L58: =L57/L53 -> 0.24569075 | M58: =M57/M53 -> 0.25973133 | N58: =N57/N53 -> 0.20792423 | O58: =O57/O53 -> 0.13963533
E59: Growth | I59: =(I57-H57)/H57 -> 0.3625498 | J59: =(J57-I57)/I57 -> -0.51608187 | K59: =(K57-J57)/J57 -> 0.47423364 | L59: =(L57-K57)/K57 -> 0.24361291 | M59: =(M57-L57)/L57 -> 0.12396725 | N59: =(N57-M57)/M57 -> -0.21917799 | O59: =(O57-N57)/N57 -> -0.3585087
E62: Net Income | H62: 14.1 | I62: 23.7 | J62: 2.2 | K62: 13.406554 | L62: 21.338006 | M62: 26.633629 | N62: 17.53226 | O62: 5.3559883
E63: Margin | H63: =H62/H53 -> 0.066042155 | I63: =I62/I53 -> 0.10016906 | J63: =J62/J53 -> 0.010742187 | K63: =K62/K53 -> 0.059222125 | L63: =L62/L53 -> 0.086389928 | M63: =M62/M53 -> 0.10141951 | N63: =N62/N53 -> 0.068447526 | O63: =O62/O53 -> 0.021890664
E64: Growth | I64: =(I62-H62)/H62 -> 0.68085106 | J64: =(J62-I62)/I62 -> -0.907173 | K64: =(K62-J62)/J62 -> 5.093888 | L64: =(L62-K62)/K62 -> 0.59161013 | M64: =(M62-L62)/L62 -> 0.24817796 | N64: =(N62-M62)/M62 -> -0.34172473 | O64: =(O62-N62)/N62 -> -0.69450667

Sheet Assumptions
B1: =Summary!B1 -> Blu Containers
B2: Inputs and Assumptions
C5: GENERAL | J5: EQUITY
C8: - | D8: First year of forecast in financial model: | G8: 2027 | J8: ="Stock Price - "&TEXT(Cover!E7,"dd/mm/yy") -> Stock Price - 23/07/26 | N8: 11.5
C9: - | D9: Three scenarios have been used for Inflation, Product Pricing | J9: ="Fully Diluted Shares O/S (MM) - Dec. 31, "&G8-1 -> Fully Diluted Shares O/S (MM) - Dec. 31, 2026 | N9: 14.8
D10: and sales volume growth | J10: Common Dividend Payout Rate | N10: 0.2
C13: PRODUCT PRICING | J13: OPERATIONS
C16: - | D16: The product pricing cases used in the model are as follows:
C17: Pricing Case | E17: =Scenarios!H6&" - "&Scenarios!L6 -> 2027 - 2031 | J17: Annual Factory Capacity (000's units): | N17: 420
C18: Base Case | E18: Research Forecast
C19: Best Case | F19: 0.04
C20: Worst Case | F20: -0.04
C23: OPERATING COSTS | J23: INTEREST RATES
C26: Cost Item | E26: =G8 -> 2027 | G26: Increases
C27: Raw Materials | E27: 226 | F27: per Unit | G27: Inflation on a unit basis | J27: Interest earned on Cash balances: | N27: 0.01
C28: Utilities | E28: 66.2 | F28: per Unit | G28: Inflation on a unit basis | J28: Interest rate on Bank Revolver: | N28: 0.06
C29: Rent | E29: 23.5 | F29: MM | G29: Inflation on a total basis | J29: Interest rate on Senior Secured Term Debt: | N29: 0.06
C30: Operating Labour | E30: 43.5 | F30: MM | G30: Inflation on a total basis
C31: Other | E31: 2 | F31: MM | G31: Inflation on a total basis
C32: SG&A | E32: 3.9 | F32: MM | G32: Inflation on a total basis
C35: DEPRECIATION | J35: TAXES
C38: - | D38: Depreciation Methodology Used: | H38: Straight Line
C39: - | D39: Years remaining for depreciation of existing assets: | H39: 25 | J39: Tax rate assumed in the model: | N39: 0.35
C40: - | D40: Years used for depreciation of new assets: | H40: 30 | J40: Additional tax assumptions in "Other Assumptions" box
B44: =Summary!B1 -> Blu Containers
B45: Inputs and Assumptions
C48: OTHER ASSUMPTIONS | J48: =G8 -> 2027 | K48: =J48+1 -> 2028 | L48: =K48+1 -> 2029 | M48: =L48+1 -> 2030 | N48: =M48+1 -> 2031
C52: Income Statement
D53: Cost Adjustments - Gain/(Loss) | G53: MM | J53: 0 | K53: 0 | L53: 0 | M53: 0 | N53: 0
C55: Cash Flow Statement
D56: Investing Activities - Other | G56: MM | J56: 0 | K56: 0 | L56: 0 | M56: 0 | N56: 0
C58: Capital Expenditures | G58: MM | J58: 16 | K58: 17 | L58: 17.3 | M58: 17.5 | N58: 18
C60: Income Tax
D61: Reduction in EBT for timing differences | G61: MM | J61: 5 | K61: 5 | L61: 5 | M61: 5 | N61: 5
C63: Working Capital Days
D64: Accounts Receivable | G64: days | J64: 48 | K64: 44 | L64: 40 | M64: 40 | N64: 40
D65: Inventories | G65: days | J65: 70 | K65: 65 | L65: 60 | M65: 60 | N65: 55
D66: Prepaid Expenses | G66: days | J66: 30 | K66: 30 | L66: 30 | M66: 30 | N66: 30
D67: Other Assets | G67: days | J67: 3 | K67: 3 | L67: 3 | M67: 3 | N67: 3
D68: Accounts Payable | G68: days | J68: 40 | K68: 40 | L68: 40 | M68: 40 | N68: 40
D69: Other Liabilities | G69: days | J69: 10 | K69: 10 | L69: 10 | M69: 10 | N69: 10
C71: Change in Debt & Equity
D72: Senior Term Debt Issuance / (Repayment) | G72: MM | J72: -25 | K72: -25 | L72: -25 | M72: -25 | N72: -25
D73: Common Stock Issuance / (Buy-back) | G73: MM | J73: 0 | K73: 0 | L73: 0 | M73: 0 | N73: 0

Sheet Scenarios
C1: =Assumptions!B1 -> Blu Containers
C2: Economic and Sales Scenarios
C6: SCENARIO SWITCH: | E6: 1 | H6: =Assumptions!G8 -> 2027 | I6: =H6+1 -> 2028 | J6: =I6+1 -> 2029 | K6: =J6+1 -> 2030 | L6: =K6+1 -> 2031
C10: ECONOMIC SCENARIOS
C12: Cost Inflation | H12: {=_xlfn.IFS($E$6=1,H14,$E$6=2,H15,$E$6=3,H16)} -> 0.02 | I12: {=_xlfn.IFS($E$6=1,I14,$E$6=2,I15,$E$6=3,I16)} -> 0.02 | J12: {=_xlfn.IFS($E$6=1,J14,$E$6=2,J15,$E$6=3,J16)} -> 0.023 | K12: {=_xlfn.IFS($E$6=1,K14,$E$6=2,K15,$E$6=3,K16)} -> 0.025 | L12: {=_xlfn.IFS($E$6=1,L14,$E$6=2,L15,$E$6=3,L16)} -> 0.025
D14: =Assumptions!C18 -> Base Case | H14: 0.02 | I14: 0.02 | J14: 0.023 | K14: 0.025 | L14: 0.025
D15: =Assumptions!C19 -> Best Case | H15: 0.018 | I15: 0.018 | J15: 0.018 | K15: 0.02 | L15: 0.02
D16: =Assumptions!C20 -> Worst Case | H16: 0.025 | I16: 0.025 | J16: 0.025 | K16: 0.025 | L16: 0.025
C21: SALES SCENARIOS
C23: Sales Price - $/Unit | H23: {=_xlfn.IFS($E$6=1,H25,$E$6=2,H26,$E$6=3,H27)} -> 765 | I23: {=_xlfn.IFS($E$6=1,I25,$E$6=2,I26,$E$6=3,I27)} -> 800 | J23: {=_xlfn.IFS($E$6=1,J25,$E$6=2,J26,$E$6=3,J27)} -> 825 | K23: {=_xlfn.IFS($E$6=1,K25,$E$6=2,K26,$E$6=3,K27)} -> 790 | L23: {=_xlfn.IFS($E$6=1,L25,$E$6=2,L26,$E$6=3,L27)} -> 750
D25: =D14 -> Base Case | H25: 765 | I25: 800 | J25: 825 | K25: 790 | L25: 750
B26: =Assumptions!F19 -> 0.04 | D26: Best Case | H26: =H$25*(1+$B26) -> 795.6 | I26: =I$25*(1+$B26) -> 832 | J26: =J$25*(1+$B26) -> 858 | K26: =K$25*(1+$B26) -> 821.6 | L26: =L$25*(1+$B26) -> 780
B27: =Assumptions!F20 -> -0.04 | D27: Worst Case | H27: =H$25*(1+$B27) -> 734.4 | I27: =I$25*(1+$B27) -> 768 | J27: =J$25*(1+$B27) -> 792 | K27: =K$25*(1+$B27) -> 758.4 | L27: =L$25*(1+$B27) -> 720
C30: Sales Volume Growth | H30: {=_xlfn.IFS($E$6=1,H32,$E$6=2,H33,$E$6=3,H34)} -> 0.05 | I30: {=_xlfn.IFS($E$6=1,I32,$E$6=2,I33,$E$6=3,I34)} -> 0.04 | J30: {=_xlfn.IFS($E$6=1,J32,$E$6=2,J33,$E$6=3,J34)} -> 0.04 | K30: {=_xlfn.IFS($E$6=1,K32,$E$6=2,K33,$E$6=3,K34)} -> 0.04 | L30: {=_xlfn.IFS($E$6=1,L32,$E$6=2,L33,$E$6=3,L34)} -> 0.04
D32: =D14 -> Base Case | H32: 0.05 | I32: 0.04 | J32: 0.04 | K32: 0.04 | L32: 0.04
D33: =D15 -> Best Case | H33: 0.05 | I33: 0.04 | J33: 0.05 | K33: 0.05 | L33: 0.04
D34: =D16 -> Worst Case | H34: 0.04 | I34: 0.04 | J34: 0.03 | K34: 0.03 | L34: 0.02

Sheet Model
O1: ="CURRENTLY RUNNING: " & UPPER(CHOOSE(Scenarios!E6,Scenarios!D14,Scenarios!D15,Scenarios!D16)) & " SCENARIO" -> CURRENTLY RUNNING: BASE CASE SCENARIO
B2: =Scenarios!C1 -> Blu Containers
B3: Revenue Schedule
K6: Projected
F7: Units | H7: =I7-1 -> 2024 | I7: =J7-1 -> 2025 | J7: =K7-1 -> 2026 | K7: =Scenarios!H6 -> 2027 | L7: =Scenarios!I6 -> 2028 | M7: =Scenarios!J6 -> 2029 | N7: =Scenarios!K6 -> 2030 | O7: =Scenarios!L6 -> 2031
B9: Pricing
C10: Gross Sales Price | F10: ($/unit) | J10: 694.4 | K10: =Scenarios!H23 -> 765 | L10: =Scenarios!I23 -> 800 | M10: =Scenarios!J23 -> 825 | N10: =Scenarios!K23 -> 790 | O10: =Scenarios!L23 -> 750
C11: Cost Inflation | F11: (%) | K11: =Scenarios!H12 -> 0.02 | L11: =Scenarios!I12 -> 0.02 | M11: =Scenarios!J12 -> 0.023 | N11: =Scenarios!K12 -> 0.025 | O11: =Scenarios!L12 -> 0.025
C12: Freight & Warehousing | F12: ($/unit) | J12: 100 | K12: =J12*(1+K11) -> 102 | L12: =K12*(1+L11) -> 104.04 | M12: =L12*(1+M11) -> 106.43292 | N12: =M12*(1+N11) -> 109.09374 | O12: =N12*(1+O11) -> 111.82109
C13: Net Sales Price | F13: ($/unit) | J13: =J10-J12 -> 594.4 | K13: =K10-K12 -> 663 | L13: =L10-L12 -> 695.96 | M13: =M10-M12 -> 718.56708 | N13: =N10-N12 -> 680.90626 | O13: =O10-O12 -> 638.17891
B16: Sales Volume
C17: Annual Factory Capacity | F17: (000's units) | K17: =Assumptions!N17 -> 420 | L17: =K17 -> 420 | M17: =L17 -> 420 | N17: =M17 -> 420 | O17: =N17 -> 420
C19: Sales Volume Growth | F19: (%) | K19: =Scenarios!H30 -> 0.05 | L19: =Scenarios!I30 -> 0.04 | M19: =Scenarios!J30 -> 0.04 | N19: =Scenarios!K30 -> 0.04 | O19: =Scenarios!L30 -> 0.04
C20: Annual Sales Volume | F20: (000's units) | J20: =J26*1000/J10 -> 344.47005 | K20: =MIN(K17,J20*(1+K19)) -> 361.69355 | L20: =MIN(L17,K20*(1+L19)) -> 376.16129 | M20: =MIN(M17,L20*(1+M19)) -> 391.20774 | N20: =MIN(N17,M20*(1+N19)) -> 406.85605 | O20: =MIN(O17,N20*(1+O19)) -> 420
C22: Implied Operating Rate | K22: =K20/K17 -> 0.86117512 | L22: =L20/L17 -> 0.89562212 | M22: =M20/M17 -> 0.931447 | N22: =N20/N17 -> 0.96870488 | O22: =O20/O17 -> 1
B25: Revenue
C26: Gross Revenue | F26: ($ MM) | J26: =J83 -> 239.2 | K26: =K20*K10/1000 -> 276.69556 | L26: =L20*L10/1000 -> 300.92903 | M26: =M20*M10/1000 -> 322.74639 | N26: =N20*N10/1000 -> 321.41628 | O26: =O20*O10/1000 -> 315
C27: Freight & Warehousing | F27: ($ MM) | J27: =J84 -> 34.4 | K27: =K20*K12/1000 -> 36.892742 | L27: =L20*L12/1000 -> 39.135821 | M27: =M20*M12/1000 -> 41.637382 | N27: =N20*N12/1000 -> 44.38545 | O27: =O20*O12/1000 -> 46.964856
C28: Net Revenue | F28: ($ MM) | J28: =J26-J27 -> 204.8 | K28: =K26-K27 -> 239.80282 | L28: =L26-L27 -> 261.79321 | M28: =M26-M27 -> 281.109 | N28: =N26-N27 -> 277.03083 | O28: =O26-O27 -> 268.03514
O31: =$O$1 -> CURRENTLY RUNNING: BASE CASE SCENARIO
B32: =B$2 -> Blu Containers
B33: Costs of Production Schedule
K36: Projected
H37: =H$7 -> 2024 | I37: =I$7 -> 2025 | J37: =J$7 -> 2026 | K37: =K$7 -> 2027 | L37: =L$7 -> 2028 | M37: =M$7 -> 2029 | N37: =N$7 -> 2030 | O37: =O$7 -> 2031
B39: Annual Sales Volume | F39: (000's units) | J39: =J20 -> 344.47005 | K39: =K20 -> 361.69355 | L39: =L20 -> 376.16129 | M39: =M20 -> 391.20774 | N39: =N20 -> 406.85605 | O39: =O20 -> 420
B40: Cost Inflation | F40: (%) | K40: =K11 -> 0.02 | L40: =L11 -> 0.02 | M40: =M11 -> 0.023 | N40: =N11 -> 0.025 | O40: =O11 -> 0.025
B42: COSTS PER UNIT
A43: 1 | C43: Variable Costs
D44: =Assumptions!C27 -> Raw Materials | F44: ($/unit) | K44: =Assumptions!E27 -> 226 | L44: =K44*(1+L$40) -> 230.52 | M44: =L44*(1+M$40) -> 235.82196 | N44: =M44*(1+N$40) -> 241.71751 | O44: =N44*(1+O$40) -> 247.76045
D45: =Assumptions!C28 -> Utilities | F45: ($/unit) | K45: =Assumptions!E28 -> 66.2 | L45: =K45*(1+L$40) -> 67.524 | M45: =L45*(1+M$40) -> 69.077052 | N45: =M45*(1+N$40) -> 70.803978 | O45: =N45*(1+O$40) -> 72.574078
D46: Total Variable Costs | F46: ($/unit) | K46: =SUM(K44:K45) -> 292.2 | L46: =SUM(L44:L45) -> 298.044 | M46: =SUM(M44:M45) -> 304.89901 | N46: =SUM(N44:N45) -> 312.52149 | O46: =SUM(O44:O45) -> 320.33452
A48: 4 | C48: Fixed Costs
D49: =Assumptions!C29 -> Rent | F49: ($/unit) | K49: =K64*1000/K$39 -> 64.972129 | L49: =L64*1000/L$39 -> 63.722665 | M49: =M64*1000/M$39 -> 62.681045 | N49: =N64*1000/N$39 -> 61.776991 | O49: =O64*1000/O$39 -> 61.339765
D50: =Assumptions!C30 -> Operating Labour | F50: ($/unit) | K50: =K65*1000/K$39 -> 120.26756 | L50: =L65*1000/L$39 -> 117.95472 | M50: =M65*1000/M$39 -> 116.02661 | N50: =N65*1000/N$39 -> 114.35315 | O50: =O65*1000/O$39 -> 113.54382
D51: Other | F51: ($/unit) | K51: =K66*1000/K$39 -> 5.5295429 | L51: =L66*1000/L$39 -> 5.4232056 | M51: =M66*1000/M$39 -> 5.334557 | N51: =N66*1000/N$39 -> 5.2576163 | O51: =O66*1000/O$39 -> 5.2204055
D52: Total Fixed Costs | F52: ($/unit) | K52: =SUM(K49:K51) -> 190.76923 | L52: =SUM(L49:L51) -> 187.10059 | M52: =SUM(M49:M51) -> 184.04222 | N52: =SUM(N49:N51) -> 181.38776 | O52: =SUM(O49:O51) -> 180.10399
C54: Total Costs | F54: ($/unit) | K54: =K52+K46 -> 482.96923 | L54: =L52+L46 -> 485.14459 | M54: =M52+M46 -> 488.94123 | N54: =N52+N46 -> 493.90925 | O54: =O52+O46 -> 500.43852
B57: COSTS IN MILLIONS
A58: 2 | C58: Variable Costs
D59: =D44 -> Raw Materials | F59: ($ MM) | K59: =K44*K$39/1000 -> 81.742742 | L59: =L44*L$39/1000 -> 86.712701 | M59: =M44*M$39/1000 -> 92.255376 | N59: =N44*N$39/1000 -> 98.344231 | O59: =O44*O$39/1000 -> 104.05939
D60: =D45 -> Utilities | F60: ($ MM) | K60: =K45*K$39/1000 -> 23.944113 | L60: =L45*L$39/1000 -> 25.399915 | M60: =M45*M$39/1000 -> 27.023478 | N60: =N45*N$39/1000 -> 28.807027 | O60: =O45*O$39/1000 -> 30.481113
D61: Total Variable Costs | F61: ($ MM) | K61: =SUM(K59:K60) -> 105.68685 | L61: =SUM(L59:L60) -> 112.11262 | M61: =SUM(M59:M60) -> 119.27885 | N61: =SUM(N59:N60) -> 127.15126 | O61: =SUM(O59:O60) -> 134.5405
A63: 3 | C63: Fixed Costs
D64: =D49 -> Rent | F64: ($ MM) | K64: =Assumptions!E29 -> 23.5 | L64: =K64*(1+L$40) -> 23.97 | M64: =L64*(1+M$40) -> 24.52131 | N64: =M64*(1+N$40) -> 25.134343 | O64: =N64*(1+O$40) -> 25.762701
D65: =D50 -> Operating Labour | F65: ($ MM) | K65: =Assumptions!E30 -> 43.5 | L65: =K65*(1+L$40) -> 44.37 | M65: =L65*(1+M$40) -> 45.39051 | N65: =M65*(1+N$40) -> 46.525273 | O65: =N65*(1+O$40) -> 47.688405
D66: =D51 -> Other | F66: ($ MM) | K66: =Assumptions!E31 -> 2 | L66: =K66*(1+L$40) -> 2.04 | M66: =L66*(1+M$40) -> 2.08692 | N66: =M66*(1+N$40) -> 2.139093 | O66: =N66*(1+O$40) -> 2.1925703
D67: Total Fixed Costs | F67: ($ MM) | K67: =SUM(K64:K66) -> 69 | L67: =SUM(L64:L66) -> 70.38 | M67: =SUM(M64:M66) -> 71.99874 | N67: =SUM(N64:N66) -> 73.798708 | O67: =SUM(O64:O66) -> 75.643676
C69: Total Costs | F69: ($ MM) | K69: =K67+K61 -> 174.68685 | L69: =L67+L61 -> 182.49262 | M69: =M67+M61 -> 191.27759 | N69: =N67+N61 -> 200.94997 | O69: =O67+O61 -> 210.18418
O72: =$O$1 -> CURRENTLY RUNNING: BASE CASE SCENARIO
B73: =B$2 -> Blu Containers
B74: Income Statement
B76: ($ Millions)
K77: Projected
H78: =H$7 -> 2024 | I78: =I$7 -> 2025 | J78: =J$7 -> 2026 | K78: =K$7 -> 2027 | L78: =L$7 -> 2028 | M78: =M$7 -> 2029 | N78: =N$7 -> 2030 | O78: =O$7 -> 2031
B80: Sales Volume | F80: (000's units) | J80: =J20 -> 344.47005 | K80: =K39 -> 361.69355 | L80: =L39 -> 376.16129 | M80: =M39 -> 391.20774 | N80: =N39 -> 406.85605 | O80: =O39 -> 420
B82: Revenue
C83: Gross Revenue | F83: Rev Sched | H83: 244.8 | I83: 269.3 | J83: 239.2 | K83: =K26 -> 276.69556 | L83: =L26 -> 300.92903 | M83: =M26 -> 322.74639 | N83: =N26 -> 321.41628 | O83: =O26 -> 315
C84: Freight & Warehousing | F84: Rev Sched | H84: 31.3 | I84: 32.7 | J84: 34.4 | K84: =K27 -> 36.892742 | L84: =L27 -> 39.135821 | M84: =M27 -> 41.637382 | N84: =N27 -> 44.38545 | O84: =O27 -> 46.964856
C85: Net Revenue | F85: Calc | H85: =+H83-H84 -> 213.5 | I85: =+I83-I84 -> 236.6 | J85: =+J83-J84 -> 204.8 | K85: =K83-K84 -> 239.80282 | L85: =L83-L84 -> 261.79321 | M85: =M83-M84 -> 281.109 | N85: =N83-N84 -> 277.03083 | O85: =O83-O84 -> 268.03514
C87: Cost of Sales | F87: Cost Sched | H87: 159.9 | I87: 164.6 | J87: 167.9 | K87: =K69 -> 174.68685 | L87: =L69 -> 182.49262 | M87: =M69 -> 191.27759 | N87: =N69 -> 200.94997 | O87: =O69 -> 210.18418
C88: S,G & A | F88: Assum | H88: 3.4 | I88: 3.6 | J88: 3.8 | K88: =Assumptions!E32 -> 3.9 | L88: =K88*(1+L$40) -> 3.978 | M88: =L88*(1+M$40) -> 4.069494 | N88: =M88*(1+N$40) -> 4.1712313 | O88: =N88*(1+O$40) -> 4.2755121
C89: Total Costs | F89: Calc | H89: =SUM(H87:H88) -> 163.3 | I89: =SUM(I87:I88) -> 168.2 | J89: =SUM(J87:J88) -> 171.7 | K89: =SUM(K87:K88) -> 178.58685 | L89: =SUM(L87:L88) -> 186.47062 | M89: =SUM(M87:M88) -> 195.34709 | N89: =SUM(N87:N88) -> 205.1212 | O89: =SUM(O87:O88) -> 214.45969
C91: Cost Adjustments - Gain/(Loss) | F91: Assum | H91: 0 | I91: 0 | J91: 0 | K91: =Assumptions!J53 -> 0 | L91: =Assumptions!K53 -> 0 | M91: =Assumptions!L53 -> 0 | N91: =Assumptions!M53 -> 0 | O91: =Assumptions!N53 -> 0
C92: EBITDA | F92: Calc | H92: =H85-H89+H91 -> 50.2 | I92: =I85-I89+I91 -> 68.4 | J92: =J85-J89+J91 -> 33.1 | K92: =K85-K89+K91 -> 61.215968 | L92: =L85-L89+L91 -> 75.322596 | M92: =M85-M89+M91 -> 85.761917 | N92: =N85-N89+N91 -> 71.909633 | O92: =O85-O89+O91 -> 53.575455
C94: Depreciation | F94: Dep'n Sched | H94: 15.4 | I94: 15.5 | J94: 15.8 | K94: =K214 -> 16.174667 | L94: =L214 -> 16.724667 | M94: =M214 -> 17.296333 | N94: =N214 -> 17.876333 | O94: =O214 -> 18.468
C95: EBIT | F95: Calc | H95: =H92-H94 -> 34.8 | I95: =I92-I94 -> 52.9 | J95: =J92-J94 -> 17.3 | K95: =K92-K94 -> 45.041301 | L95: =L92-L94 -> 58.597929 | M95: =M92-M94 -> 68.465583 | N95: =N92-N94 -> 54.0333 | O95: =O92-O94 -> 35.107455
C97: Interest Expense | F97: Debt Sched | H97: 15 | I97: 15 | J97: 14 | K97: =K322 -> 11.997 | L97: =L322 -> 10.85961 | M97: =M322 -> 9.1919742 | N97: =N322 -> 7.4356563 | O97: =O322 -> 5.9290109
C98: EBT | F98: Calc | H98: =H95-H97 -> 19.8 | I98: =I95-I97 -> 37.9 | J98: =J95-J97 -> 3.3 | K98: =K95-K97 -> 33.044301 | L98: =L95-L97 -> 47.738319 | M98: =M95-M97 -> 59.273609 | N98: =N95-N97 -> 46.597643 | O98: =O95-O97 -> 29.178444
C100: Current Income Taxes | F100: Tax Sched | H100: 3 | I100: 8 | J100: 0 | K100: =K237 -> 9.8155054 | L100: =L237 -> 14.958412 | M100: =M237 -> 18.995763 | N100: =N237 -> 14.559175 | O100: =O237 -> 8.4624554
C101: Deferred Income Taxes | F101: Tax Sched | H101: 2.7 | I101: 6.2 | J101: 1.1 | K101: =K238 -> 1.75 | L101: =L238 -> 1.75 | M101: =M238 -> 1.75 | N101: =N238 -> 1.75 | O101: =O238 -> 1.75
C102: Total Income Taxes | F102: SUM | H102: =SUM(H100:H101) -> 5.7 | I102: =SUM(I100:I101) -> 14.2 | J102: =SUM(J100:J101) -> 1.1 | K102: =SUM(K100:K101) -> 11.565505 | L102: =SUM(L100:L101) -> 16.708412 | M102: =SUM(M100:M101) -> 20.745763 | N102: =SUM(N100:N101) -> 16.309175 | O102: =SUM(O100:O101) -> 10.212455
C104: Net Income | F104: Calc | H104: =H98-H102 -> 14.1 | I104: =I98-I102 -> 23.7 | J104: =J98-J102 -> 2.2 | K104: =K98-K102 -> 21.478796 | L104: =L98-L102 -> 31.029908 | M104: =M98-M102 -> 38.527846 | N104: =N98-N102 -> 30.288468 | O104: =O98-O102 -> 18.965989
B107: Margins
C108: EBITDA Margin | H108: =H92/H85 -> 0.23512881 | I108: =I92/I85 -> 0.28909552 | J108: =J92/J85 -> 0.16162109 | K108: =K92/K85 -> 0.25527626 | L108: =L92/L85 -> 0.28771791 | M108: =M92/M85 -> 0.3050842 | N108: =N92/N85 -> 0.25957267 | O108: =O92/O85 -> 0.1998822
C109: EBIT Margin | H109: =H95/H85 -> 0.16299766 | I109: =I95/I85 -> 0.22358411 | J109: =J95/J85 -> 0.084472656 | K109: =K95/K85 -> 0.1878264 | L109: =L95/L85 -> 0.22383288 | M109: =M95/M85 -> 0.24355528 | N109: =N95/N85 -> 0.19504435 | O109: =O95/O85 -> 0.13098079
C110: Return on Equity | H110: =H104/H184 -> 0.058823529 | I110: =I104/I184 -> 0.091611906 | J110: =J104/J184 -> 0.0085106383 | K110: =K104/K184 -> 0.077911198 | L110: =L104/L184 -> 0.10325853 | M110: =M104/M184 -> 0.11628266 | N110: =N104/N184 -> 0.085185249 | O110: =O104/O184 -> 0.051158108
O113: =$O$1 -> CURRENTLY RUNNING: BASE CASE SCENARIO
B114: =B$2 -> Blu Containers
B115: Cash Flow Statement
B117: ($ Millions)
K118: Projected
H119: =H$7 -> 2024 | I119: =I$7 -> 2025 | J119: =J$7 -> 2026 | K119: =K$7 -> 2027 | L119: =L$7 -> 2028 | M119: =M$7 -> 2029 | N119: =N$7 -> 2030 | O119: =O$7 -> 2031
B120: Operating Activities
C121: Net Income | F121: Inc Stmt | H121: 14.1 | I121: 23.7 | J121: 2.2 | K121: =K104 -> 21.478796 | L121: =L104 -> 31.029908 | M121: =M104 -> 38.527846 | N121: =N104 -> 30.288468 | O121: =O104 -> 18.965989
C122: Depreciation & Amortization | F122: Inc Stmt | H122: 15.4 | I122: 15.5 | J122: 15.8 | K122: =K94 -> 16.174667 | L122: =L94 -> 16.724667 | M122: =M94 -> 17.296333 | N122: =N94 -> 17.876333 | O122: =O94 -> 18.468
C123: Deferred Income Taxes | F123: Inc Stmt | H123: 2.7 | I123: 6.2 | J123: 1.1 | K123: =K101 -> 1.75 | L123: =L101 -> 1.75 | M123: =M101 -> 1.75 | N123: =N101 -> 1.75 | O123: =O101 -> 1.75
C124: Changes in working capital | F124: WC Sched | H124: 0 | I124: 0 | J124: 0 | K124: =K275 -> -0.40120217 | L124: =L275 -> 1.4953364 | M124: =M275 -> 2.0653267 | N124: =N275 -> -0.69256189 | O124: =O275 -> 2.7771983
C125: Operating Cash Flow | F125: Calc | H125: =SUM(H121:H124) -> 32.2 | I125: =SUM(I121:I124) -> 45.4 | J125: =SUM(J121:J124) -> 19.1 | K125: =SUM(K121:K124) -> 39.00226 | L125: =SUM(L121:L124) -> 50.999911 | M125: =SUM(M121:M124) -> 59.639506 | N125: =SUM(N121:N124) -> 49.22224 | O125: =SUM(O121:O124) -> 41.961187
B128: Investing Activities
C129: CAPEX | F129: Assum | H129: -14.1 | I129: -15 | J129: -15.5 | K129: =-Assumptions!J58 -> -16 | L129: =-Assumptions!K58 -> -17 | M129: =-Assumptions!L58 -> -17.3 | N129: =-Assumptions!M58 -> -17.5 | O129: =-Assumptions!N58 -> -18
C130: Other | F130: Assum | H130: -5 | I130: 4 | J130: 3 | K130: =Assumptions!J56 -> 0 | L130: =Assumptions!K56 -> 0 | M130: =Assumptions!L56 -> 0 | N130: =Assumptions!M56 -> 0 | O130: =Assumptions!N56 -> 0
C131: Investing Cash Flow | F131: Calc | H131: =SUM(H129:H130) -> -19.1 | I131: =SUM(I129:I130) -> -11 | J131: =SUM(J129:J130) -> -12.5 | K131: =SUM(K129:K130) -> -16 | L131: =SUM(L129:L130) -> -17 | M131: =SUM(M129:M130) -> -17.3 | N131: =SUM(N129:N130) -> -17.5 | O131: =SUM(O129:O130) -> -18
B134: Financing Activities
C135: Revolver Issuance / (Repayment) | F135: Debt Sched | H135: 0 | I135: 0 | J135: 0 | K135: =K306 -> 5.9934989 | L135: =L306 -> -2.7939292 | M135: =M306 -> -3.1995698 | N135: =N306 -> 0 | O135: =O306 -> 0
C136: Term Debt Issuance / (Repayment) | F136: Debt Sched | H136: -25 | I136: -25 | J136: -25 | K136: =K315 -> -25 | L136: =L315 -> -25 | M136: =M315 -> -25 | N136: =N315 -> -25 | O136: =O315 -> -25
C137: Common Shares Issuance/ (Buy-Back) | F137: Equity Sched | H137: 0 | I137: 0 | J137: 0 | K137: =K335 -> 0 | L137: =L335 -> 0 | M137: =M335 -> 0 | N137: =N335 -> 0 | O137: =O335 -> 0
C138: Common Dividends | F138: Equity Sched | H138: -2.8 | I138: -4.7 | J138: -2.4 | K138: =-K340 -> -4.2957591 | L138: =-L340 -> -6.2059815 | M138: =-M340 -> -7.7055692 | N138: =-N340 -> -6.0576936 | O138: =-O340 -> -3.7931977
C139: Financing Cash Flow | F139: Calc | H139: =SUM(H135:H138) -> -27.8 | I139: =SUM(I135:I138) -> -29.7 | J139: =SUM(J135:J138) -> -27.4 | K139: =SUM(K135:K138) -> -23.30226 | L139: =SUM(L135:L138) -> -33.999911 | M139: =SUM(M135:M138) -> -35.905139 | N139: =SUM(N135:N138) -> -31.057694 | O139: =SUM(O135:O138) -> -28.793198
B142: Change in the Cash Position | H142: =H139+H131+H125 -> -14.7 | I142: =I139+I131+I125 -> 4.7 | J142: =J139+J131+J125 -> -20.8 | K142: =K125+K131+K139 -> -0.3 | L142: =L125+L131+L139 -> 0 | M142: =M125+M131+M139 -> 6.4343671 | N142: =N125+N131+N139 -> 0.66454599 | O142: =O125+O131+O139 -> -4.8320108
B143: Beginning Cash | H143: 31.1 | I143: =+H144 -> 16.4 | J143: =+I144 -> 21.1 | K143: =J144 -> 0.3 | L143: =K144 -> -3.5527137e-15 | M143: =L144 -> -3.5527137e-15 | N143: =M144 -> 6.4343671 | O143: =N144 -> 7.0989131
...
